coursera_helper/__init__.py
coursera_helper/api.py
coursera_helper/cauth.py
coursera_helper/commandline.py
coursera_helper/cookies.py
coursera_helper/coursera_dl.py
coursera_helper/credentials.py
coursera_helper/define.py
coursera_helper/downloaders.py
coursera_helper/extractors.py
coursera_helper/filtering.py
coursera_helper/formatting.py
coursera_helper/network.py
coursera_helper/parallel.py
coursera_helper/playlist.py
coursera_helper/utils.py
coursera_helper/workflow.py
coursera_helper-0.12.3.dist-info/METADATA
coursera_helper-0.12.3.dist-info/WHEEL
coursera_helper-0.12.3.dist-info/entry_points.txt
coursera_helper-0.12.3.dist-info/licenses/AUTHORS.md
coursera_helper-0.12.3.dist-info/licenses/LICENSE
coursera_helper-0.12.3.dist-info/RECORD
