Metadata-Version: 2.1
Name: coursera-helper
Version: 0.12.3
Summary: Script for downloading Coursera.org videos and naming them.
Project-URL: Homepage, https://github.com/csyezheng/coursera-helper
Maintainer-email: Ye Zheng <csyezheng@gmail.com>
License:                    GNU LESSER GENERAL PUBLIC LICENSE
License-File: AUTHORS.md
License-File: LICENSE
Keywords: MOOCs,coursera,coursera-dl,download,education,video
Classifier: Development Status :: 4 - Beta
Classifier: Environment :: Console
Classifier: Intended Audience :: End Users/Desktop
Classifier: License :: OSI Approved :: GNU Lesser General Public License v3 or later (LGPLv3+)
Classifier: Operating System :: OS Independent
Classifier: Programming Language :: Python
Classifier: Programming Language :: Python :: 3
Classifier: Programming Language :: Python :: 3.8
Classifier: Programming Language :: Python :: 3.9
Classifier: Programming Language :: Python :: 3.10
Classifier: Programming Language :: Python :: 3.11
Classifier: Programming Language :: Python :: Implementation :: CPython
Classifier: Programming Language :: Python :: Implementation :: PyPy
Classifier: Topic :: Education
Requires-Dist: attrs==18.1.0
Requires-Dist: beautifulsoup4>=4.1.3
Requires-Dist: browser-cookie3>=0.19.1
Requires-Dist: configargparse>=0.12.0
Requires-Dist: keyring>=4.0
Requires-Dist: playwright>=1.38.0
Requires-Dist: pyasn1>=0.1.7
Requires-Dist: requests>=2.10.0
Requires-Dist: six>=1.5.0
Requires-Dist: urllib3>=1.23
Provides-Extra: dev
Requires-Dist: coverage>=3.7; extra == 'dev'
Requires-Dist: keyrings-alt; extra == 'dev'
Requires-Dist: mock>=1.0.1; extra == 'dev'
Requires-Dist: pytest; extra == 'dev'
Requires-Dist: pytest-cov; extra == 'dev'
Requires-Dist: pytest-xdist; extra == 'dev'
Requires-Dist: tox; extra == 'dev'
